{"cameraMode":{"drawMode":0,"name":"Shaded","section":"Shading Mode"},"sceneLighting":true,"audioPlay":false,"sceneViewState":{"showFog":true,"showMaterialUpdate":false,"showSkybox":true,"showFlares":true,"showImageEffects":true,"showParticleSystems":true},"in2DMode":false,"pivot":{"x":29.117244720458986,"y":17.1761417388916,"z":-1.5449161529541016},"rotation":{"x":0.1784171164035797,"y":0.4788796901702881,"z":-0.10098850727081299,"w":0.8540116548538208},"size":3.1005120277404787,"orthographic":false}